stypes/__init__.py
stypes/date.py
stypes/mapping.py
stypes/numeric.py
stypes/odict.py
stypes/sequence.py
stypes/spec.py
stypes/test_date.py
stypes/test_mapping.py
stypes/test_numeric.py
stypes/test_sequence.py
stypes/test_string.py
stypes/util.py
stypes/version.py
stypes-0.23.2.dist-info/LICENSE
stypes-0.23.2.dist-info/METADATA
stypes-0.23.2.dist-info/WHEEL
stypes-0.23.2.dist-info/top_level.txt
stypes-0.23.2.dist-info/RECORD
